pyproject.toml
setup.py
app/__init__.py
app/app.py
app/api/__init__.py
app/api/api_v1/__init__.py
app/api/api_v1/router.py
app/api/api_v1/handlers/__init__.py
app/api/api_v1/handlers/forecast.py
app/api/api_v1/handlers/user.py
app/api/auth/__init__.py
app/api/auth/jwt.py
app/api/deps/__init__.py
app/api/deps/user_deps.py
app/core/__init__.py
app/core/config.py
app/core/security.py
app/models/__init__.py
app/models/parameters.py
app/models/user_model.py
app/prompts/__init__.py
app/prompts/main.py
app/schemas/__init__.py
app/schemas/auth_schema.py
app/schemas/user_schema.py
app/services/__init__.py
app/services/langchain_service.py
app/services/multivariate_timeseries.py
app/services/openai_service.py
app/services/test.py
app/services/user_service.py
applicare_ai.egg-info/PKG-INFO
applicare_ai.egg-info/SOURCES.txt
applicare_ai.egg-info/dependency_links.txt
applicare_ai.egg-info/entry_points.txt
applicare_ai.egg-info/requires.txt
applicare_ai.egg-info/top_level.txt
logs/__init__.py
logs/loggers/__init__.py
logs/loggers/logger.py
test/__init__.py
test1/__init__.py
test1/test.py
utils/__init__.py
utils/cli.py
utils/thresholds.py
utils/version.py
utils/console/__init__.py
utils/console/banner.py
utils/console/chart.py
utils/console/io.py
utils/console/shell.py
utils/docker/__init__.py
utils/docker/util.py